bavapi/__init__.py
bavapi/_batched.py
bavapi/_fetcher.py
bavapi/_jupyter.py
bavapi/client.py
bavapi/config.py
bavapi/exceptions.py
bavapi/filters.py
bavapi/http.py
bavapi/py.typed
bavapi/query.py
bavapi/sync.py
bavapi/tools.py
bavapi/typing.py
bavapi/_reference/__init__.py
bavapi/_reference/generate_reference.py
bavapi/_reference/int_enum.py
bavapi/parsing/__init__.py
bavapi/parsing/params.py
bavapi/parsing/responses.py
wpp_bavapi-1.1.0.dist-info/LICENSE
wpp_bavapi-1.1.0.dist-info/METADATA
wpp_bavapi-1.1.0.dist-info/WHEEL
wpp_bavapi-1.1.0.dist-info/entry_points.txt
wpp_bavapi-1.1.0.dist-info/top_level.txt
wpp_bavapi-1.1.0.dist-info/RECORD
