Metadata-Version: 2.1
Name: wpp-bavapi
Version: 1.1.0
Summary: Python consumer for the WPPBAV Fount API.
Author-email: Ignacio Maiz Vilches <ignacio.maiz@bavgroup.com>
License: Apache 2.0
Project-URL: homepage, https://wppbav.github.io/bavapi-sdk-python/
Project-URL: repository, https://github.com/wppbav/wpp-bavapi/
Project-URL: api_reference, https://developer.wppbav.com/docs/2.x/intro
Keywords: wpp-bavapi,bavapi,bavgroup,bav,brandasset,brandassetvaluator,wppbav,wpp,fount
Classifier: Development Status :: 5 - Production/Stable
Classifier: Intended Audience :: Science/Research
Classifier: Intended Audience :: Developers
Classifier: License :: OSI Approved :: Apache Software License
Classifier: Operating System :: OS Independent
Classifier: Programming Language :: Python :: 3
Classifier: Programming Language :: Python :: 3.8
Classifier: Programming Language :: Python :: 3.9
Classifier: Programming Language :: Python :: 3.10
Classifier: Programming Language :: Python :: 3.11
Classifier: Programming Language :: Python :: 3.12
Classifier: Typing :: Typed
Requires-Python: >=3.8
License-File: LICENSE
Requires-Dist: httpx >=0.20
Requires-Dist: nest-asyncio >=1.5
Requires-Dist: pandas >=1.0
Requires-Dist: pydantic >=2.0
Requires-Dist: tqdm >=4.0
Requires-Dist: typing-extensions >=4.6 ; python_version < "3.12"
Provides-Extra: dev
Requires-Dist: black ; extra == 'dev'
Requires-Dist: nox ; extra == 'dev'
Requires-Dist: ipykernel ; extra == 'dev'
Provides-Extra: doc
Requires-Dist: mkdocs ; extra == 'doc'
Requires-Dist: mkdocs-material[imaging] ; extra == 'doc'
Requires-Dist: mkdocstrings[python] ; extra == 'doc'
Requires-Dist: mkdocs-gen-files ; extra == 'doc'
Requires-Dist: mkdocs-literate-nav ; extra == 'doc'
Requires-Dist: mkdocs-section-index ; extra == 'doc'
Requires-Dist: mike ; extra == 'doc'
Provides-Extra: lint
Requires-Dist: isort ; extra == 'lint'
Requires-Dist: mypy ; extra == 'lint'
Requires-Dist: pylint ; extra == 'lint'
Requires-Dist: pandas-stubs ; extra == 'lint'
Provides-Extra: test
Requires-Dist: coverage ; extra == 'test'
Requires-Dist: pytest ; extra == 'test'
Requires-Dist: pytest-asyncio ; extra == 'test'
Requires-Dist: python-dotenv ; extra == 'test'
